odoo/addons/l10n_it_fatturapa_in/README.rst
odoo/addons/l10n_it_fatturapa_in/__init__.py
odoo/addons/l10n_it_fatturapa_in/__manifest__.py
odoo/addons/l10n_it_fatturapa_in/i18n/it.po
odoo/addons/l10n_it_fatturapa_in/i18n/l10n_it_fatturapa_in.pot
odoo/addons/l10n_it_fatturapa_in/models/__init__.py
odoo/addons/l10n_it_fatturapa_in/models/account.py
odoo/addons/l10n_it_fatturapa_in/models/attachment.py
odoo/addons/l10n_it_fatturapa_in/models/company.py
odoo/addons/l10n_it_fatturapa_in/models/partner.py
odoo/addons/l10n_it_fatturapa_in/readme/CONFIGURE.rst
odoo/addons/l10n_it_fatturapa_in/readme/CONTRIBUTORS.rst
odoo/addons/l10n_it_fatturapa_in/readme/DESCRIPTION.rst
odoo/addons/l10n_it_fatturapa_in/readme/INSTALL.rst
odoo/addons/l10n_it_fatturapa_in/readme/USAGE.rst
odoo/addons/l10n_it_fatturapa_in/security/ir.model.access.csv
odoo/addons/l10n_it_fatturapa_in/security/rules.xml
odoo/addons/l10n_it_fatturapa_in/static/description/icon.png
odoo/addons/l10n_it_fatturapa_in/static/description/index.html
odoo/addons/l10n_it_fatturapa_in/static/src/img/icon.png
odoo/addons/l10n_it_fatturapa_in/tests/__init__.py
odoo/addons/l10n_it_fatturapa_in/tests/test_import_fatturapa_xml.py
odoo/addons/l10n_it_fatturapa_in/tests/data/IT01234567890_FPR03.base64.xml.p7m
odoo/addons/l10n_it_fatturapa_in/tests/data/IT01234567890_FPR03.xml
odoo/addons/l10n_it_fatturapa_in/tests/data/IT01234567890_FPR03.xml.p7m
odoo/addons/l10n_it_fatturapa_in/tests/data/IT01234567890_FPR04.base64.xml.p7m
odoo/addons/l10n_it_fatturapa_in/tests/data/IT01234567890_FPR04.xml
odoo/addons/l10n_it_fatturapa_in/tests/data/IT01234567890_FPR05.xml
odoo/addons/l10n_it_fatturapa_in/tests/data/IT02780790107_11004.xml
odoo/addons/l10n_it_fatturapa_in/tests/data/IT02780790107_11005.xml
odoo/addons/l10n_it_fatturapa_in/tests/data/IT02780790107_11006.xml
odoo/addons/l10n_it_fatturapa_in/tests/data/IT02780790107_11007.xml
odoo/addons/l10n_it_fatturapa_in/tests/data/IT03638121008_X11111.xml
odoo11_addon_l10n_it_fatturapa_in-11.0.1.1.6.dist-info/METADATA
odoo11_addon_l10n_it_fatturapa_in-11.0.1.1.6.dist-info/WHEEL
odoo11_addon_l10n_it_fatturapa_in-11.0.1.1.6.dist-info/top_level.txt
odoo11_addon_l10n_it_fatturapa_in-11.0.1.1.6.dist-info/RECORD
