Metadata-Version: 2.1
Name: odoo11-addon-l10n-it-fatturapa-in
Version: 11.0.1.1.6
Summary: Ricezione fatture elettroniche
Home-page: https://github.com/OCA/l10n-italy/tree/11.0/l10n_it_fatturapa_in
Author: Agile Business Group, Innoviu, Odoo Community Association (OCA)
Author-email: support@odoo-community.org
License: LGPL-3
Platform: UNKNOWN
Classifier: Programming Language :: Python
Classifier: Framework :: Odoo
Classifier: License :: OSI Approved :: GNU Lesser General Public License v3 (LGPLv3)
Classifier: Development Status :: 4 - Beta
Requires-Python: >=2.7, !=3.0.*, !=3.1.*, !=3.2.*, !=3.3.*, !=3.4.*
Requires-Dist: odoo11-addon-l10n-it-fatturapa
Requires-Dist: odoo11-addon-l10n-it-withholding-tax-causali
Requires-Dist: odoo (<11.1dev,>=11.0a)
